LICENSE
MANIFEST.in
README.md
setup.py
keras_cor/__init__.py
keras_cor/cor.py
keras_cor.egg-info/PKG-INFO
keras_cor.egg-info/SOURCES.txt
keras_cor.egg-info/dependency_links.txt
keras_cor.egg-info/requires.txt
keras_cor.egg-info/top_level.txt
keras_cor.egg-info/zip-safe
test/__init__.py
test/test_cor.py